AUTHORS.rst
CONTRIBUTING.rst
LICENSE
MANIFEST.in
README.rst
requirements.txt
setup.cfg
setup.py
versioneer.py
docs/Makefile
docs/make.bat
docs/source/conf.py
docs/source/index.rst
recordits/__init__.py
recordits/_version.py
recordits.egg-info/PKG-INFO
recordits.egg-info/SOURCES.txt
recordits.egg-info/dependency_links.txt
recordits.egg-info/entry_points.txt
recordits.egg-info/requires.txt
recordits.egg-info/top_level.txt
recordits/tests/__init__.py
recordits/tests/conftest.py
recordits/tests/test_blank.py