Metadata-Version: 1.1
Name: recordits
Version: 0.0.0
Summary: Recording points for LCLS-II
Home-page: https://github.com/pcdshub/recordits
Author: SLAC National Accelerator Laboratory
Author-email: UNKNOWN
License: BSD
Platform: UNKNOWN
Classifier: Development Status :: 2 - Pre-Alpha
Classifier: Natural Language :: English
Classifier: Programming Language :: Python :: 3
